sekuensial/sr_ff.vhdl
-- generated by Digital. Don't modify this file!
-- Any changes will be lost if this file is regenerated.

LIBRARY ieee;
USE ieee.std_logic_1164.all;
USE ieee.numeric_std.all;

entity sr_ff is
  port (
    S: in std_logic;
    R: in std_logic;
    Clk: in std_logic;
    Q: out std_logic;
    Qo: out std_logic);
end sr_ff;

architecture Behavioral of sr_ff is
  signal Qo_temp: std_logic;
  signal Q_temp: std_logic;
begin
  Q_temp <= NOT ((S AND Clk) OR Qo_temp);
  Qo_temp <= NOT (Q_temp OR (Clk AND R));
  Q <= Q_temp;
  Qo <= Qo_temp;
end Behavioral;

sekuensial/sr_ff_tb.vhdl
LIBRARY ieee;
USE ieee.std_logic_1164.all;
USE ieee.numeric_std.all;

entity sr_ff_tb is
    end sr_ff_tb;

architecture test of sr_ff_tb is
    component sr_ff
        port
        (
            S: in std_ulogic;
            R: in std_ulogic;
            Clk: in std_ulogic;
            Q: out std_ulogic;
            Qo: out std_ulogic
        );
    end component;

    signal S, R, Clk, Q, Qo: std_ulogic;

begin
    sr_latch: sr_ff port map(S=>S, R=>R, Clk=>Clk, Q=>Q, Qo=>Qo);

    process begin
        S <= 'X';
        R <= 'X';
        Clk <= 'X';
        wait for 1 ns;

        S <= '0';
        R <= '0';
        Clk <= '0';
        wait for 1 ns;

        S <= '1';
        R <= '0';
        Clk <= '0';
        wait for 1 ns;

        S <= '0';
        R <= '1';
        Clk <= '0';
        wait for 1 ns;

        S <= '1';
        R <= '1';
        Clk <= '0';
        wait for 1 ns;

        S <= '0';
        R <= '0';
        Clk <= '1';
        wait for 1 ns;

        S <= '1';
        R <= '0';
        Clk <= '1';
        wait for 1 ns;

        S <= '0';
        R <= '1';
        Clk <= '1';
        wait for 1 ns;

        S <= '1';
        R <= '1';
        Clk <= '1';
        wait for 1 ns;

        assert false report "end of test";
        wait;

        end process;
    end test;

sekuensial/sr_ff_tb.vcd
$date
  Sat Mar 25 19:10:39 2023
$end
$version
  GHDL v0
$end
$timescale
  1 fs
$end
$scope module standard $end
$upscope $end
$scope module std_logic_1164 $end
$upscope $end
$scope module numeric_std $end
$upscope $end
$scope module sr_ff_tb $end
$var reg 1 ! s $end
$var reg 1 " r $end
$var reg 1 # clk $end
$var reg 1 $ q $end
$var reg 1 % qo $end
$scope module sr_latch $end
$var reg 1 & s $end
$var reg 1 ' r $end
$var reg 1 ( clk $end
$var reg 1 ) q $end
$var reg 1 * qo $end
$var reg 1 + qo_temp $end
$var reg 1 , q_temp $end
$upscope $end
$upscope $end
$enddefinitions $end
#0
X!
X"
X#
U$
U%
X&
X'
X(
U)
U*
U+
U,
#1000000
0!
0"
0#
0&
0'
0(
#2000000
1!
1&
#3000000
0!
1"
0&
1'
#4000000
1!
1&
#5000000
0!
0"
1#
0&
0'
1(
#6000000
1!
0$
1%
1&
0)
1*
1+
0,
#7000000
0!
1"
1$
0%
0&
1'
1)
0*
0+
1,
#8000000
1!
0$
1&
0)
0,
