kombinasional/full_adder.vhdl
-- generated by Digital. Don't modify this file!
-- Any changes will be lost if this file is regenerated.

LIBRARY ieee;
USE ieee.std_logic_1164.all;
USE ieee.numeric_std.all;

entity fa is
  port (
    A: in std_logic;
    B: in std_logic;
    Ci: in std_logic;
    S: out std_logic;
    Co: out std_logic);
end fa;

architecture Behavioral of fa is
  signal s0: std_logic;
begin
  s0 <= (A XOR B);
  S <= (s0 XOR Ci);
  Co <= ((s0 AND Ci) OR (A AND B));
end Behavioral;

kombinasional/full_adder_tb.vhdl
library ieee;
USE ieee.std_logic_1164.all;
USE ieee.numeric_std.all;

entity fa_tb is
    end fa_tb;

architecture test of fa_tb is
    component fa
        port(
            A: in std_logic;
            B: in std_logic;
            Ci: in std_logic;
            S: out std_logic;
            Co: out std_logic
        );
    end component;

    signal A,B,Ci,S,Co: std_logic;

begin
    full_adder: fa port map(A=>A, B=>B, S=>S, Ci=>Ci, Co=>Co);

    process begin
        A <= 'X';
        B <= 'X';
        Ci <= 'X';
        wait for 1 ns;

        A <= '0';
        B <= '0';
        Ci <= '0';
        wait for 1 ns;

        A <= '1';
        B <= '0';
        Ci <= '0';
        wait for 1 ns;

        A <= '0';
        B <= '1';
        Ci <= '0';
        wait for 1 ns;

        A <= '1';
        B <= '1';
        Ci <= '0';
        wait for 1 ns;

        A <= '0';
        B <= '0';
        Ci <= '1';
        wait for 1 ns;

        A <= '1';
        B <= '0';
        Ci <= '1';
        wait for 1 ns;

        A <= '0';
        B <= '1';
        Ci <= '1';
        wait for 1 ns;

        A <= '1';
        B <= '1';
        Ci <= '1';
        wait for 1 ns;

        assert false report "end of test";
        wait;

        end process;
    end test;

kombinasional/fa_tb.vcd
$date
  Sat Mar 25 13:15:55 2023
$end
$version
  GHDL v0
$end
$timescale
  1 fs
$end
$scope module standard $end
$upscope $end
$scope module std_logic_1164 $end
$upscope $end
$scope module numeric_std $end
$upscope $end
$scope module fa_tb $end
$var reg 1 ! a $end
$var reg 1 " b $end
$var reg 1 # ci $end
$var reg 1 $ s $end
$var reg 1 % co $end
$scope module full_adder $end
$var reg 1 & a $end
$var reg 1 ' b $end
$var reg 1 ( ci $end
$var reg 1 ) s $end
$var reg 1 * co $end
$var reg 1 + s0 $end
$upscope $end
$upscope $end
$enddefinitions $end
#0
X!
X"
X#
X$
X%
X&
X'
X(
X)
X*
X+
#1000000
0!
0"
0#
0$
0%
0&
0'
0(
0)
0*
0+
#2000000
1!
1$
1&
1)
1+
#3000000
0!
1"
0&
1'
#4000000
1!
0$
1%
1&
0)
1*
0+
#5000000
0!
0"
1#
1$
0%
0&
0'
1(
1)
0*
#6000000
1!
0$
1%
1&
0)
1*
1+
#7000000
0!
1"
0&
1'
#8000000
1!
1$
1&
1)
0+
