embed_take_home/comparator.vhdl
library IEEE;
use IEEE.STD_LOGIC_1164.ALL;

entity COMPR_2 is 
	port (x, y : in std_logic_vector(1 downto 0); 
	xgty, xlty : buffer std_logic; 
	xeqy : out std_logic); 

end COMPR_2;

architecture COMPR_DFL of COMPR_2 is
begin 
	xgty <= (x(1) and not(y(1))) or ((x(0) and not(y(1))) and not(y(0))) or (not(x(0) and not(x(1))) and y(0));
	xlty <= (y(1) and not(x(1))) or ((not(x(0) and y(0))) and y(1)) or ((not(x(0)) and not(x(1))) and y(0)); 
	xeqy <= xgty nor xlty;
end COMPR_DFL;

embed_take_home/comparator_tb.vhdl
library ieee;
use ieee.std_logic_1164.all;
use ieee.numeric_std.all;

entity comparator_tb is
  end comparator_tb;

architecture test of comparator_tb is
  component COMPR_2
  port(
    x, y : in std_logic_vector(1 downto 0); 
    xgty, xlty : buffer std_logic; 
    xeqy : out std_logic
  );
  end component;

  -- inputs
  signal x,y : std_logic_vector(1 downto 0) := (others => '0');
  -- outputs
  signal xgty,xlty,xeqy : std_logic;

begin
  COMP2BIT : COMPR_2 port map(
    x => x,
    y => y,
    xgty => xgty,
    xlty => xlty,
    xeqy => xeqy
  );

  stim_proc: process
  begin
    for i in 0 to 3 loop
      x <= std_logic_vector(to_unsigned(i,2));
      y <= std_logic_vector(to_unsigned(i+1,2));
      wait for 20 ns;
    end loop;

    for i in 0 to 3 loop
      x <= std_logic_vector(to_unsigned(1+1,2));
      y <= std_logic_vector(to_unsigned(i,2));
      wait for 20 ns;
    end loop;

    for i in 0 to 3 loop
      x <= std_logic_vector(to_unsigned(i,2));
      y <= std_logic_vector(to_unsigned(i,2));
      wait for 20 ns;
    end loop;
    wait;

    assert false report "end of test";
  end process;
end;

embed_take_home/comparator_tb.vcd
$date
  Sat Apr  8 12:23:47 2023
$end
$version
  GHDL v0
$end
$timescale
  1 fs
$end
$scope module standard $end
$upscope $end
$scope module std_logic_1164 $end
$upscope $end
$scope module numeric_std $end
$upscope $end
$scope module comparator_tb $end
$var reg 2 ! x[1:0] $end
$var reg 2 " y[1:0] $end
$var reg 1 # xgty $end
$var reg 1 $ xlty $end
$var reg 1 % xeqy $end
$scope module comp2bit $end
$var reg 2 & x[1:0] $end
$var reg 2 ' y[1:0] $end
$var reg 1 ( xgty $end
$var reg 1 ) xlty $end
$var reg 1 * xeqy $end
$upscope $end
$upscope $end
$enddefinitions $end
#0
b00 !
b01 "
1#
1$
0%
b00 &
b01 '
1(
1)
0*
#20000000
b01 !
b10 "
0#
b01 &
b10 '
0(
#40000000
b10 !
b11 "
1#
b10 &
b11 '
1(
#60000000
b11 !
b00 "
0$
b11 &
b00 '
0)
#80000000
b10 !
b10 &
#100000000
b01 "
b01 '
#120000000
b10 "
0#
1$
b10 '
0(
1)
#140000000
b11 "
1#
b11 '
1(
#160000000
b00 !
b00 "
0#
0$
1%
b00 &
b00 '
0(
0)
1*
#180000000
b01 !
b01 "
b01 &
b01 '
#200000000
b10 !
b10 "
1$
0%
b10 &
b10 '
1)
0*
#220000000
b11 !
b11 "
1#
0$
b11 &
b11 '
1(
0)
